notifyrelay/__init__.py
notifyrelay/client.py
notifyrelay/exceptions.py
notifyrelay/subscriber.py
notifyrelay-0.1.0.dist-info/licenses/LICENSE
tests/__init__.py
tests/test_client.py
notifyrelay-0.1.0.dist-info/METADATA
notifyrelay-0.1.0.dist-info/WHEEL
notifyrelay-0.1.0.dist-info/top_level.txt
notifyrelay-0.1.0.dist-info/RECORD
