Metadata-Version: 2.4
Name: notifyrelay
Version: 0.1.0
Summary: Python client for NotifyRelay pub/sub messaging service
Home-page: https://github.com/magland/notifyrelay
Author: NotifyRelay Contributors
License: MIT
Project-URL: Homepage, https://github.com/magland/notifyrelay
Classifier: Development Status :: 3 - Alpha
Classifier: Intended Audience :: Developers
Classifier: License :: OSI Approved :: MIT License
Classifier: Programming Language :: Python :: 3
Classifier: Programming Language :: Python :: 3.7
Classifier: Programming Language :: Python :: 3.8
Classifier: Programming Language :: Python :: 3.9
Classifier: Programming Language :: Python :: 3.10
Classifier: Programming Language :: Python :: 3.11
Requires-Python: >=3.7
License-File: LICENSE
Requires-Dist: requests>=2.25.0
Provides-Extra: dev
Requires-Dist: pytest>=6.0; extra == "dev"
Requires-Dist: pytest-cov>=2.0; extra == "dev"
Dynamic: home-page
Dynamic: license-file
Dynamic: requires-python
